nngame/__init__.py
nngame/easygame.py
nngame-0.0.3.dist-info/METADATA
nngame-0.0.3.dist-info/WHEEL
nngame-0.0.3.dist-info/licenses/LICENSE
nngame-0.0.3.dist-info/RECORD
